{
    "configurations": [
        {
            "name": "Win32",
            "includePath": [
                "${workspaceFolder}/**",
                "${workspaceFolder}/src/SDL2/x86_64-w64-mingw32/include/SDL2", // SDL2 header folder
            ],
            "defines": [
                "_DEBUG",
                "UNICODE",
                "_UNICODE"
            ],
            "windowsSdkVersion": "10.0.22621.0",
            "compilerPath": "cl.exe",
            // Windows MingW: "cl.exe"
            // Windows Clang: "clang.exe"
            "cStandard": "c17",
            "cppStandard": "c++17",
            "intelliSenseMode": "windows-msvc-x64"
        }
    ],
    "version": 4
}